jagger_ext.cpython-311-aarch64-linux-gnu.so
jagger-0.1.20.dist-info/jagger.GPL
jagger-0.1.20.dist-info/WHEEL
jagger-0.1.20.dist-info/METADATA
jagger-0.1.20.dist-info/LICENSE
jagger-0.1.20.dist-info/entry_points.txt
jagger-0.1.20.dist-info/RECORD
jagger-0.1.20.dist-info/jagger.BSD
jagger-0.1.20.dist-info/top_level.txt
jagger-0.1.20.dist-info/jagger.LGPL
jagger/main.py
jagger/_version.py
jagger/python-binding-jagger.cc
jagger/__init__.py
jagger/ccedar_core.h
jagger/jagger.h
