Metadata-Version: 2.1
Name: jagger
Version: 0.1.20
License-File: LICENSE
License-File: jagger.BSD
License-File: jagger.GPL
License-File: jagger.LGPL
